concept_graph_builder/__init__.py
concept_graph_builder/data_loader.py
concept_graph_builder/graph_builder.py
concept_graph_builder/llm_extractor.py
concept_graph_builder/visualizer.py
ConceptGraphBuilder-0.1.0.dist-info/LICENSE
ConceptGraphBuilder-0.1.0.dist-info/METADATA
ConceptGraphBuilder-0.1.0.dist-info/WHEEL
ConceptGraphBuilder-0.1.0.dist-info/top_level.txt
ConceptGraphBuilder-0.1.0.dist-info/RECORD
