Metadata-Version: 2.1
Name: ConceptGraphBuilder
Version: 0.1.0
Summary: A Python library for extracting concepts using LLMs and building knowledge graphs
Home-page: https://github.com/kshitijkutumbe/ConceptGraphBuilder
Author: Kshitij Kutumbe
Author-email: kshitijkutumbe@gmail.com
Classifier: Programming Language :: Python :: 3
Classifier: License :: OSI Approved :: MIT License
Classifier: Operating System :: OS Independent
License-File: LICENSE
Requires-Dist: pandas >=2.1.3
Requires-Dist: numpy >=1.26.2
Requires-Dist: networkx >=3.2.1
Requires-Dist: seaborn >=0.13.0
Requires-Dist: langchain >=0.0.335
Requires-Dist: pypdf >=3.17.0
Requires-Dist: pyvis >=0.3.1
Requires-Dist: tqdm >=4.38
Requires-Dist: yachalk >=0.1.5
Requires-Dist: langchain-openai
